Workbook
Name Slicer_Category: ""
Name Slicer_Product: ""
Name Slicer_Region: ""

Sheet Raw_Data
A1: Order_ID | B1: Date | C1: Region | D1: Product | E1: Category | F1: Sales | G1: Quantity | H1: Cost | I1: Profit | J1: Profit_Margin
A2: 1001 | B2: 45658 | C2: North | D2: Laptop | E2: Technology | F2: 1200 | G2: 2 | H2: 800 | I2: =Raw_Data!$F2-Raw_Data!$H2 -> 400 | J2: =Raw_Data!$I2/Raw_Data!$F2 -> 0.33333333
A3: 1002 | B3: 45659 | C3: South | D3: Mouse | E3: Technology | F3: 200 | G3: 5 | H3: 120 | I3: =Raw_Data!$F3-Raw_Data!$H3 -> 80 | J3: =Raw_Data!$I3/Raw_Data!$F3 -> 0.4
A4: 1003 | B4: 45660 | C4: East | D4: Keyboard | E4: Technology | F4: 450 | G4: 3 | H4: 300 | I4: =Raw_Data!$F4-Raw_Data!$H4 -> 150 | J4: =Raw_Data!$I4/Raw_Data!$F4 -> 0.33333333
A5: 1004 | B5: 45662 | C5: West | D5: Monitor | E5: Technology | F5: 800 | G5: 2 | H5: 550 | I5: =Raw_Data!$F5-Raw_Data!$H5 -> 250 | J5: =Raw_Data!$I5/Raw_Data!$F5 -> 0.3125
A6: 1005 | B6: 45665 | C6: North | D6: Printer | E6: Technology | F6: 1500 | G6: 1 | H6: 1000 | I6: =Raw_Data!$F6-Raw_Data!$H6 -> 500 | J6: =Raw_Data!$I6/Raw_Data!$F6 -> 0.33333333
A7: 1006 | B7: 45667 | C7: South | D7: Desk | E7: Furniture | F7: 900 | G7: 3 | H7: 600 | I7: =Raw_Data!$F7-Raw_Data!$H7 -> 300 | J7: =Raw_Data!$I7/Raw_Data!$F7 -> 0.33333333
A8: 1007 | B8: 45669 | C8: East | D8: Chair | E8: Furniture | F8: 350 | G8: 7 | H8: 210 | I8: =Raw_Data!$F8-Raw_Data!$H8 -> 140 | J8: =Raw_Data!$I8/Raw_Data!$F8 -> 0.4
A9: 1008 | B9: 45672 | C9: West | D9: Table | E9: Furniture | F9: 500 | G9: 4 | H9: 320 | I9: =Raw_Data!$F9-Raw_Data!$H9 -> 180 | J9: =Raw_Data!$I9/Raw_Data!$F9 -> 0.36
A10: 1009 | B10: 45675 | C10: North | D10: Phone | E10: Technology | F10: 950 | G10: 2 | H10: 600 | I10: =Raw_Data!$F10-Raw_Data!$H10 -> 350 | J10: =Raw_Data!$I10/Raw_Data!$F10 -> 0.36842105
A11: 1010 | B11: 45677 | C11: South | D11: Tablet | E11: Technology | F11: 1100 | G11: 2 | H11: 700 | I11: =Raw_Data!$F11-Raw_Data!$H11 -> 400 | J11: =Raw_Data!$I11/Raw_Data!$F11 -> 0.36363636
A12: 1001 | B12: 45658 | C12: North | D12: Laptop | E12: Technology | F12: 1200 | G12: 2 | H12: 700 | I12: =Raw_Data!$F12-Raw_Data!$H12 -> 500 | J12: =Raw_Data!$I12/Raw_Data!$F12 -> 0.41666667
A13: 1002 | B13: 45659 | C13: South | D13: Mouse | E13: Technology | F13: 200 | G13: 5 | H13: 700 | I13: =Raw_Data!$F13-Raw_Data!$H13 -> -500 | J13: =Raw_Data!$I13/Raw_Data!$F13 -> -2.5
... A201: 1010 | B201: 45677 | C201: South | D201: Tablet | E201: Technology | F201: 1100 | G201: 2 | H201: 700 | I201: =Raw_Data!$F201-Raw_Data!$H201 -> 400 | J201: =Raw_Data!$I201/Raw_Data!$F201 -> 0.36363636

Sheet Top_Analysis
A1: Row Labels | B1: Sum of Sales | J1: Row Labels | K1: Sum of Sales
A2: Chair | B2: 7000 | J2: Desk | K2: 18000
A3: Desk | B3: 18000 | J3: Laptop | K3: 24000
A4: Keyboard | B4: 9000 | J4: Phone | K4: 19000
A5: Laptop | B5: 24000 | J5: Printer | K5: 30000
A6: Monitor | B6: 16000 | J6: Tablet | K6: 22000
A7: Mouse | B7: 4000 | J7: Grand Total | K7: 113000
A8: Phone | B8: 19000
A9: Printer | B9: 30000
A10: Table | B10: 10000
A11: Tablet | B11: 22000
A12: Grand Total | B12: 159000

Sheet Pivot_Analysis
A1: Revenue by Region | D1: Profit by Product
A3: Row Labels | B3: Sum of Sales | D3: Row Labels | E3: Sum of Profit
A4: East | B4: 0.10062893 | D4: Chair | E4: -6510
A5: North | B5: 0.4591195 | D5: Desk | E5: 4100
A6: South | B6: 0.27672956 | D6: Keyboard | E6: -4600
A7: West | B7: 0.16352201 | D7: Laptop | E7: 9900
A8: Grand Total | B8: 1 | D8: Monitor | E8: 2150
D9: Mouse | E9: -9420
D10: Phone | E10: 5100
D11: Printer | E11: 15700
D12: Table | E12: -3620
D13: Tablet | E13: 8000
D14: Grand Total | E14: 20800
A16: Monthly Revenue Trend
D17: Row Labels | E17: Sum of Profit
A18: Row Labels | B18: Sum of Sales | D18: East | E18: -11110
A19: Jan | B19: 159000 | D19: North | E19: 30700
A20: Grand Total | B20: 159000 | D20: South | E20: 2680
D21: West | E21: -1470
D22: Grand Total | E22: 20800

Sheet Calculations
A1: Total Revenue | B1: =SUM(Raw_Data!$F$2:$F$201) -> 159000
A2: Total Profit | B2: =SUM(Raw_Data!$I$2:$I$201) -> 20800
A3: Average Profit Margin | B3: =AVERAGE(Raw_Data!$J$2:$J$201) -> -0.22280676

Sheet Dashboard
A1: Retail Sales Performance Dashboard 2025
D2: Revenue Contribution by Region
A3: Total Revenue | B3: =Calculations!B1 -> 159000 | D3: Row Labels | E3: Sum of Sales
A4: Total Profit | B4: =Calculations!B2 -> 20800 | D4: East | E4: 0.10062893
A5: Avg Profit Margin | B5: =Calculations!B3 -> -0.22280676 | D5: North | E5: 0.4591195
D6: South | E6: 0.27672956
D7: West | E7: 0.16352201
D8: Grand Total | E8: 1
J24: Most Profitable Region: | K24: =Pivot_Analysis!B5 -> 0.4591195

Sheet Executive_Summary
